aiosend/__init__.py
aiosend/__meta__.py
aiosend/exceptions.py
aiosend/loggers.py
aiosend/py.typed
aiosend/_events/__init__.py
aiosend/_events/handler.py
aiosend/_events/observer.py
aiosend/_events/payload_data.py
aiosend/_events/router.py
aiosend/_methods/__init__.py
aiosend/_methods/base.py
aiosend/_methods/create_check.py
aiosend/_methods/create_invoice.py
aiosend/_methods/delete_check.py
aiosend/_methods/delete_invoice.py
aiosend/_methods/get_balance.py
aiosend/_methods/get_checks.py
aiosend/_methods/get_currencies.py
aiosend/_methods/get_exchange_rates.py
aiosend/_methods/get_invoices.py
aiosend/_methods/get_me.py
aiosend/_methods/get_stats.py
aiosend/_methods/get_transfers.py
aiosend/_methods/transfer.py
aiosend/_typing/__init__.pyi
aiosend/_typing/protocols/__init__.pyi
aiosend/_typing/protocols/client.pyi
aiosend/_typing/protocols/client_webhook_manager.pyi
aiosend/_typing/protocols/get_balance.pyi
aiosend/_typing/protocols/get_checks.pyi
aiosend/_typing/protocols/get_exchange_rates.pyi
aiosend/_typing/protocols/get_invoices.pyi
aiosend/_typing/protocols/session_network.pyi
aiosend/_utils/__init__.py
aiosend/_utils/check_token.py
aiosend/_utils/list_serializer.py
aiosend/_utils/sync.py
aiosend/client/__init__.py
aiosend/client/client.py
aiosend/client/client.pyi
aiosend/client/network.py
aiosend/client/session/__init__.py
aiosend/client/session/aiohttp.py
aiosend/client/session/base.py
aiosend/enums/__init__.py
aiosend/enums/asset.py
aiosend/enums/check_status.py
aiosend/enums/currency_type.py
aiosend/enums/fiat.py
aiosend/enums/invoice_status.py
aiosend/enums/paid_btn_name.py
aiosend/enums/update_type.py
aiosend/polling/__init__.py
aiosend/polling/base.py
aiosend/polling/check.py
aiosend/polling/invoice.py
aiosend/polling/manager.py
aiosend/polling/router.py
aiosend/tools/__init__.py
aiosend/tools/delete_all_checks.py
aiosend/tools/delete_all_invoices.py
aiosend/tools/exchange.py
aiosend/tools/get_balance_by_asset.py
aiosend/tools/get_check.py
aiosend-3.0.4.dist-info/METADATA
aiosend-3.0.4.dist-info/WHEEL
aiosend-3.0.4.dist-info/licenses/LICENSE.txt
aiosend-3.0.4.dist-info/RECORD
