Metadata-Version: 2.4
Name: aiosend
Version: 3.0.4
Summary: sync & async Crypto Pay API client.
Project-URL: Repository, https://github.com/vovchic17/aiosend
Project-URL: Documentation, https://aiosend.rtfd.io/
Author-email: VoVcHiC <tsvetkovvova17@gmail.com>
License-Expression: MIT
License-File: LICENSE.txt
Keywords: Crypto Bot,Crypto Pay API,CryptoBot,CryptoPayAPI,crypto pay,crypto pay api,cryptobot,cryptopayapi
Classifier: License :: OSI Approved :: MIT License
Classifier: Programming Language :: Python
Classifier: Programming Language :: Python :: 3 :: Only
Classifier: Programming Language :: Python :: 3.10
Classifier: Programming Language :: Python :: 3.11
Classifier: Programming Language :: Python :: 3.12
Classifier: Programming Language :: Python :: 3.13
Classifier: Programming Language :: Python :: 3.14
Classifier: Topic :: Software Development :: Libraries
Classifier: Topic :: Software Development :: Quality Assurance
Requires-Python: >=3.10
Requires-Dist: aiohttp>=3.9.0
Requires-Dist: certifi>=2023.7.22
Requires-Dist: magic-filter>=1.0.12
Requires-Dist: pydantic<2.12,>=2.4.1
Provides-Extra: docs
Requires-Dist: furo; extra == 'docs'
Requires-Dist: matplotlib; extra == 'docs'
Requires-Dist: sphinx-autodoc-typehints; extra == 'docs'
Requires-Dist: sphinx-copybutton; extra == 'docs'
Requires-Dist: sphinx-intl; extra == 'docs'
Requires-Dist: sphinxext-opengraph; extra == 'docs'
Provides-Extra: fastapi
Requires-Dist: fastapi[standard]; extra == 'fastapi'
Provides-Extra: flask
Requires-Dist: flask; extra == 'flask'
Provides-Extra: test
Requires-Dist: pytest; extra == 'test'
Requires-Dist: pytest-asyncio; extra == 'test'
